<mods xmlns="http://www.loc.gov/mods/v3" xmlns:xsi="http://www.w3.org/2001/XMLSchema-instance" xmlns:xlink="http://www.w3.org/1999/xlink" version="3.6" xsi:schemaLocation="http://www.loc.gov/mods/v3 http://cluster-schemas.uni-hd.de/modsCluster.xsd" ID="uuid-A4562FAE-818A-44F8-B6F3-3FE695635BE9">
    <name type="personal">
        <namePart lang="chi" script="Hant">桃水痴史著</namePart>
        <namePart lang="chi" transliteration="chinese/ala-lc">Tao shui chi shizhe</namePart>
        <role>
            <roleTerm type="text">author</roleTerm>
        </role>
    </name>
    <titleInfo lang="chi" script="Hant">
        <title>人椅子</title>
    </titleInfo>
    <titleInfo type="translated" transliteration="chinese/ala-lc">
        <title>Ren yizi</title>
    </titleInfo>
    <note type="citation">日本書目志,卷十四,小說門,小說,p 1199</note>
    <language>
        <languageTerm type="code" authority="iso639-2b"/>
    </language>
    <recordInfo>
        <recordOrigin>exported from MHDB database</recordOrigin>
    </recordInfo>
    <identifier type="mh">book_8428</identifier>
</mods>