<mods xmlns="http://www.loc.gov/mods/v3"
      xmlns:xsi="http://www.w3.org/2001/XMLSchema-instance"
      xmlns:xlink="http://www.w3.org/1999/xlink"
      version="3.6"
      xsi:schemaLocation="http://www.loc.gov/mods/v3 http://cluster-schemas.uni-hd.de/modsCluster.xsd"
      ID="uuid-61D07FC0-F829-4BE0-8295-ACF92EACB93A">
    <name type="personal">
        <namePart lang="chi" script="Hant">西村於蒐著</namePart>
        <role>
            <roleTerm type="text">author</roleTerm>
        </role>
    </name>
    <titleInfo lang="chi" script="Hant">
        <title>奇術秘法</title>
    </titleInfo>
    <note type="citation">日本書目志,卷二,理學門,化學,p 631</note>
    <note type="price">一角</note>
    <identifier type="mh">book_1392</identifier>
</mods>
