<mods xmlns="http://www.loc.gov/mods/v3" xmlns:xsi="http://www.w3.org/2001/XMLSchema-instance" xmlns:xlink="http://www.w3.org/1999/xlink" version="3.6" xsi:schemaLocation="http://www.loc.gov/mods/v3 http://cluster-schemas.uni-hd.de/modsCluster.xsd" ID="uuid-1CA5B671-14A5-40F2-832E-C62FC85B0546">
    <name type="personal">
        <namePart lang="chi" script="Hant">堀中東洲編</namePart>
        <namePart lang="chi" transliteration="chinese/ala-lc">Ku Zhongdong zhou bian</namePart>
        <role>
            <roleTerm type="text">author</roleTerm>
        </role>
    </name>
    <titleInfo lang="chi" script="Hant">
        <title>廣益 漢語伊吕波字引</title>
    </titleInfo>
    <titleInfo type="translated" transliteration="chinese/ala-lc">
        <title>Guangyi Hanyu yi lü bo zi yin</title>
    </titleInfo>
    <note type="citation">日本書目志,卷十二,文字語言門,伊吕波引,p 1073</note>
    <note type="price">三角</note>
    <language>
        <languageTerm type="code" authority="iso639-2b"/>
    </language>
    <recordInfo>
        <recordOrigin>exported from MHDB database</recordOrigin>
    </recordInfo>
    <identifier type="mh">book_6656</identifier>
</mods>