<mods xmlns="http://www.loc.gov/mods/v3"
      xmlns:xsi="http://www.w3.org/2001/XMLSchema-instance"
      xmlns:xlink="http://www.w3.org/1999/xlink"
      version="3.6"
      xsi:schemaLocation="http://www.loc.gov/mods/v3 http://cluster-schemas.uni-hd.de/modsCluster.xsd"
      ID="uuid-0F997B35-2D85-4389-A678-44A3EF909B3D">
    <titleInfo lang="chi" script="Hant">
        <title>眼科指蒙</title>
    </titleInfo>
    <note type="citation">增版東西學書錄,卷四,醫學第二十三,內科,p 245</note>
    <abstract lang="chi" type="summary">眼科指蒙一卷附圖 益智書會本一冊 [英]稻維德譯，星垣述，眼症有內外之別，書分三十七篇，已具大略，其教學者 以剖析猪羊目，互驗部位病症，是誠西國之醫術。</abstract>
    <identifier type="mh">book_750</identifier>
</mods>
