<mods xmlns="http://www.loc.gov/mods/v3" xmlns:xsi="http://www.w3.org/2001/XMLSchema-instance" xmlns:xlink="http://www.w3.org/1999/xlink" version="3.6" xsi:schemaLocation="http://www.loc.gov/mods/v3 http://cluster-schemas.uni-hd.de/modsCluster.xsd" ID="uuid-991F65B1-FAA1-45F3-AA0B-87DCA6B92F15"><name type="personal" xlink:href=""><namePart lang="chi" script="Hant">石井光政著</namePart><role><roleTerm type="text">author</roleTerm></role></name><titleInfo lang="chi" script="Hant"><title>和漢曆原考</title></titleInfo><note type="citation">日本書目志,卷二,理學門,曆書,p 636</note><note type="price">一角二分</note><identifier type="mh">book_1442</identifier></mods>