<mods xmlns="http://www.loc.gov/mods/v3" xmlns:xsi="http://www.w3.org/2001/XMLSchema-instance" xmlns:xlink="http://www.w3.org/1999/xlink" version="3.6" xsi:schemaLocation="http://www.loc.gov/mods/v3 http://cluster-schemas.uni-hd.de/modsCluster.xsd" ID="uuid-95348C92-4EFF-4841-B824-5E339AC100F4">
    <name type="personal">
        <namePart lang="chi" script="Hant">杉浦辰己、棚橋松本</namePart>
        <namePart lang="chi" transliteration="chinese/ala-lc">Shan pu chen ji, peng qiao song ben</namePart>
        <role>
            <roleTerm type="text">author</roleTerm>
        </role>
    </name>
    <titleInfo lang="chi" script="Hant">
        <title>日本通鑑</title>
    </titleInfo>
    <titleInfo type="translated" transliteration="chinese/ala-lc">
        <title>Riben tong jian</title>
    </titleInfo>
    <note type="citation">日本書目志,卷四,圖史門,日本史,p 703</note>
    <note type="price">二圓一角</note>
    <language>
        <languageTerm type="code" authority="iso639-2b"/>
    </language>
    <recordInfo>
        <recordOrigin>exported from MHDB database</recordOrigin>
    </recordInfo>
    <identifier type="mh">book_2221</identifier>
</mods>