<mods xmlns="http://www.loc.gov/mods/v3"
      xmlns:xsi="http://www.w3.org/2001/XMLSchema-instance"
      xmlns:xlink="http://www.w3.org/1999/xlink"
      version="3.6"
      xsi:schemaLocation="http://www.loc.gov/mods/v3 http://cluster-schemas.uni-hd.de/modsCluster.xsd"
      ID="uuid-00679904-57E8-4EFB-B9DF-4F8FA9953DF3">
    <name type="personal">
        <namePart lang="chi" script="Hant">合肥李鴻章原本　林正弘校定增補</namePart>
        <role>
            <roleTerm type="text">author</roleTerm>
        </role>
    </name>
    <titleInfo lang="chi" script="Hant">
        <title>訂正 李氏歷代地理沿革圖</title>
    </titleInfo>
    <note type="citation">日本書目志,卷四,圖史門,亞細亞地圖,p 695</note>
    <note type="price">七角五分</note>
    <identifier type="mh">book_2120</identifier>
</mods>
