<mods xmlns="http://www.loc.gov/mods/v3"
      xmlns:xsi="http://www.w3.org/2001/XMLSchema-instance"
      xmlns:xlink="http://www.w3.org/1999/xlink"
      version="3.6"
      xsi:schemaLocation="http://www.loc.gov/mods/v3 http://cluster-schemas.uni-hd.de/modsCluster.xsd"
      ID="uuid-920D063F-3313-47ED-83F8-FDAF19E2DF13">
    <titleInfo lang="chi" script="Hant">
        <title>古易察病傳</title>
    </titleInfo>
    <note type="citation">日本書目志,卷十三,美術門,占筮書,p 1134</note>
    <note type="price">一角二分</note>
    <identifier type="mh">book_7481</identifier>
</mods>
