<mods xmlns="http://www.loc.gov/mods/v3" xmlns:xsi="http://www.w3.org/2001/XMLSchema-instance" xmlns:xlink="http://www.w3.org/1999/xlink" version="3.6" xsi:schemaLocation="http://www.loc.gov/mods/v3 http://cluster-schemas.uni-hd.de/modsCluster.xsd" ID="uuid-54B48E24-DD03-4F0F-A15C-64B9862D5968">
    <titleInfo lang="chi" script="Hant">
        <title>游厯亞中記</title>
    </titleInfo>
    <titleInfo type="translated" transliteration="chinese/ala-lc">
        <title>You li ya zhong ji</title>
    </titleInfo>
    <note type="citation">增版東西學書錄,卷四,遊記第二十八,p 269</note>
    <abstract lang="chi" type="summary">游厯亞中記一卷 滙報本 [瑞典]赫定著，滙報館譯，書中記赫君遊厯亞洲中央，備嘗辛苦，由俄國烏拉山 抵燕京，由烏拉山出帕米爾山，跋涉於回部、西藏間，該處中俄英三國交界為 必爭之地，故所記特詳，所言加斯加城之冰山光怪陸離，讀之令人生噤，惟 西北苦寒缺水，驚沙萬里，資斧費至四萬餘佛郎，則此遊誠不易矣。 [顧補]</abstract>
    <language>
        <languageTerm type="code" authority="iso639-2b"/>
    </language>
    <recordInfo>
        <recordOrigin>exported from MHDB database</recordOrigin>
    </recordInfo>
    <identifier type="mh">book_843</identifier>
</mods>