<mods xmlns="http://www.loc.gov/mods/v3"
      xmlns:xsi="http://www.w3.org/2001/XMLSchema-instance"
      xmlns:xlink="http://www.w3.org/1999/xlink"
      version="3.6"
      xsi:schemaLocation="http://www.loc.gov/mods/v3 http://cluster-schemas.uni-hd.de/modsCluster.xsd"
      ID="uuid-A4A0CEF9-1160-4544-A51C-4E977841A991">
    <titleInfo lang="chi" script="Hant">
        <title>度量衡全書 《法律叢書》第廿九卷</title>
    </titleInfo>
    <note type="citation">日本書目志,卷九,商業門,度量衡書,p 897</note>
    <note type="price">七分</note>
    <identifier type="mh">book_4305</identifier>
</mods>
