<mods xmlns="http://www.loc.gov/mods/v3" xmlns:xsi="http://www.w3.org/2001/XMLSchema-instance" xmlns:xlink="http://www.w3.org/1999/xlink" version="3.6" xsi:schemaLocation="http://www.loc.gov/mods/v3 http://cluster-schemas.uni-hd.de/modsCluster.xsd" ID="uuid-EDD328F5-CEF8-4D61-B2F0-E40B7E76E148"><name type="personal" xlink:href=""><namePart lang="chi" script="Hant">佐藤信淵著</namePart><role><roleTerm type="text">author</roleTerm></role></name><titleInfo lang="chi" script="Hant"><title>培養秘錄</title></titleInfo><note type="citation">日本書目志,卷七,農業門,圃業書,p 837</note><note type="price">七角五分</note><identifier type="mh">book_3730</identifier></mods>