<mods xmlns="http://www.loc.gov/mods/v3" xmlns:xsi="http://www.w3.org/2001/XMLSchema-instance"
    xmlns:xlink="http://www.w3.org/1999/xlink" version="3.6"
    xsi:schemaLocation="http://www.loc.gov/mods/v3 http://cluster-schemas.uni-hd.de/modsCluster.xsd"
    ID="uuid-6B31DFA8-C3E0-4D85-8746-FF2A6E6699AB">
    <name type="personal">
        <namePart lang="chi" script="Hant">田中有年編</namePart>
        <namePart lang="chi" transliteration="chinese/ala-lc">Tian zhong younian bian</namePart>
        <role>
            <roleTerm type="text">author</roleTerm>
        </role>
    </name>
    <titleInfo lang="chi" script="Hant">
        <title>朝野萬通用文</title>
    </titleInfo>
    <titleInfo type="translated" transliteration="chinese/ala-lc">
        <title>Chaoye wan tongyong wen</title>
    </titleInfo>
    <note type="citation">日本書目志,卷十二,文字語言門,用文章,p 1048</note>
    <note type="price">二角</note>
    <language>
        <languageTerm type="code" authority="iso639-2b"/>
    </language>
    <recordInfo>
        <recordOrigin>exported from MHDB database</recordOrigin>
    </recordInfo>
    <identifier type="mh">book_6293</identifier>
</mods>
