<mods xmlns="http://www.loc.gov/mods/v3"
      xmlns:xsi="http://www.w3.org/2001/XMLSchema-instance"
      xmlns:xlink="http://www.w3.org/1999/xlink"
      version="3.6"
      xsi:schemaLocation="http://www.loc.gov/mods/v3 http://cluster-schemas.uni-hd.de/modsCluster.xsd"
      ID="uuid-73B6C1F2-5B81-487F-A583-877ABF65AD47">
    <titleInfo lang="chi" script="Hant">
        <title>和歌三代集</title>
    </titleInfo>
    <note type="citation">日本書目志,卷十一,文學門,歌集,p 979</note>
    <note type="price">五角五分</note>
    <identifier type="mh">book_5328</identifier>
</mods>
