<mods xmlns="http://www.loc.gov/mods/v3" xmlns:xsi="http://www.w3.org/2001/XMLSchema-instance" xmlns:xlink="http://www.w3.org/1999/xlink" version="3.6" xsi:schemaLocation="http://www.loc.gov/mods/v3 http://cluster-schemas.uni-hd.de/modsCluster.xsd" ID="uuid-39751B95-3EA8-4A7A-8647-5DF6515467C3">
    <titleInfo lang="chi" script="Hant">
        <title>彥山觀現誓助劍 演劇脚本</title>
    </titleInfo>
    <titleInfo type="translated" transliteration="chinese/ala-lc">
        <title>Yan shan guan xian shi zhu jian yanju jiaoben</title>
    </titleInfo>
    <note type="citation">日本書目志,卷十一,文學門,戲曲,p 1006</note>
    <note type="price">一角二分</note>
    <language>
        <languageTerm type="code" authority="iso639-2b"/>
    </language>
    <recordInfo>
        <recordOrigin>exported from MHDB database</recordOrigin>
    </recordInfo>
    <identifier type="mh">book_5721</identifier>
</mods>