<mods xmlns="http://www.loc.gov/mods/v3" xmlns:xsi="http://www.w3.org/2001/XMLSchema-instance" xmlns:xlink="http://www.w3.org/1999/xlink" version="3.6" xsi:schemaLocation="http://www.loc.gov/mods/v3 http://cluster-schemas.uni-hd.de/modsCluster.xsd" ID="uuid-346C9C63-29E7-4B46-9114-AE8178721A27">
    <name type="personal">
        <namePart lang="chi" script="Hant">渡邊國武編</namePart>
        <namePart lang="chi" transliteration="chinese/ala-lc">Du bian guo wu bian</namePart>
        <role>
            <roleTerm type="text">author</roleTerm>
        </role>
    </name>
    <titleInfo lang="chi" script="Hant">
        <title>天龍道人傳</title>
    </titleInfo>
    <titleInfo type="translated" transliteration="chinese/ala-lc">
        <title>Tianlong Daoren chuan</title>
    </titleInfo>
    <note type="citation">日本書目志,卷四,圖史門,傳記,p 722</note>
    <note type="price">三角</note>
    <language>
        <languageTerm type="code" authority="iso639-2b"/>
    </language>
    <recordInfo>
        <recordOrigin>exported from MHDB database</recordOrigin>
    </recordInfo>
    <identifier type="mh">book_2490</identifier>
</mods>