<mods xmlns="http://www.loc.gov/mods/v3"
      xmlns:xsi="http://www.w3.org/2001/XMLSchema-instance"
      xmlns:xlink="http://www.w3.org/1999/xlink"
      version="3.6"
      xsi:schemaLocation="http://www.loc.gov/mods/v3 http://cluster-schemas.uni-hd.de/modsCluster.xsd"
      ID="uuid-EC058DF8-5606-41A8-A47A-82A70C5F455D">
    <name type="personal">
        <namePart lang="chi" script="Hant">太田健吉編</namePart>
        <role>
            <roleTerm type="text">author</roleTerm>
        </role>
    </name>
    <titleInfo lang="chi" script="Hant">
        <title>學校用日本地圖</title>
    </titleInfo>
    <note type="citation">日本書目志,卷四,圖史門,地圖小學校用,p 684</note>
    <note type="price">一角八分</note>
    <identifier type="mh">book_1961</identifier>
</mods>
