<mods xmlns="http://www.loc.gov/mods/v3" xmlns:xsi="http://www.w3.org/2001/XMLSchema-instance"
    xmlns:xlink="http://www.w3.org/1999/xlink" version="3.6"
    xsi:schemaLocation="http://www.loc.gov/mods/v3 http://cluster-schemas.uni-hd.de/modsCluster.xsd"
    ID="uuid-6588028C-E8DE-4E1A-A043-5C461727DC24">
    <name type="personal">
        <namePart lang="chi" script="Hant">近松門左衛門作</namePart>
        <role>
            <roleTerm type="text">author</roleTerm>
        </role>
    </name>
    <titleInfo lang="chi" script="Hant">
        <title>心中宵庚申 外一種合本 </title>
    </titleInfo>
    <note type="citation">日本書目志,卷十一,文學門,戲曲,p 1005</note>
    <note type="price">七分</note>
    <identifier type="mh">book_5705</identifier>
</mods>
