<mods xmlns="http://www.loc.gov/mods/v3" xmlns:xsi="http://www.w3.org/2001/XMLSchema-instance" xmlns:xlink="http://www.w3.org/1999/xlink" version="3.6" xsi:schemaLocation="http://www.loc.gov/mods/v3 http://cluster-schemas.uni-hd.de/modsCluster.xsd" ID="uuid-1C43C440-989F-443A-87E6-EDB4394A6055">
    <name type="personal">
        <namePart lang="chi" script="Hant">文部省藏板</namePart>
        <namePart lang="chi" transliteration="chinese/ala-lc">Wenbu sheng cang ban</namePart>
        <role>
            <roleTerm type="text">author</roleTerm>
        </role>
    </name>
    <titleInfo lang="chi" script="Hant">
        <title>《百科全書》 氣中現象學</title>
    </titleInfo>
    <titleInfo type="translated" transliteration="chinese/ala-lc">
        <title>«Baikequanshu» qi zhong xianxiangxue</title>
    </titleInfo>
    <note type="citation">日本書目志,卷二,理學門,氣象學,p 636</note>
    <note type="price">二角</note>
    <language>
        <languageTerm type="code" authority="iso639-2b"/>
    </language>
    <recordInfo>
        <recordOrigin>exported from MHDB database</recordOrigin>
    </recordInfo>
    <identifier type="mh">book_1448</identifier>
</mods>