<mods xmlns="http://www.loc.gov/mods/v3"
      xmlns:xsi="http://www.w3.org/2001/XMLSchema-instance"
      xmlns:xlink="http://www.w3.org/1999/xlink"
      version="3.6"
      xsi:schemaLocation="http://www.loc.gov/mods/v3 http://cluster-schemas.uni-hd.de/modsCluster.xsd"
      ID="uuid-53F7DF39-1916-4D19-A76C-4FBA7B0B5516">
    <titleInfo lang="chi" script="Hant">
        <title>臨陣管見</title>
    </titleInfo>
    <note type="citation">增版東西學書錄,卷一,兵制第五,陸軍,p 94</note>
    <abstract lang="chi" type="summary">臨陣管見允卷 製造局本四冊　富強叢書本 [布]斯拉弗司著，[美]金楷理譯，趙元益述，書成於一千八百六十六年布國大勝 奧國後，據事立說，非同虛擬，每論本國軍事不善一一指明其錯誤，以垂鑑戒， 復採各國修改軍法，與法國一千八百六十六年後修改之法引為比較，以證 利弊。講武事者宜細讀之。</abstract>
    <identifier type="mh">book_185</identifier>
</mods>
