<mods xmlns="http://www.loc.gov/mods/v3" xmlns:xsi="http://www.w3.org/2001/XMLSchema-instance" xmlns:xlink="http://www.w3.org/1999/xlink" version="3.6" xsi:schemaLocation="http://www.loc.gov/mods/v3 http://cluster-schemas.uni-hd.de/modsCluster.xsd" ID="uuid-7940A11E-F77F-43D6-9B3A-4639C079FD2F"><titleInfo lang="chi" script="Hant"><title>電氣之死刑 《探偵小說》第三 </title></titleInfo><note type="citation">日本書目志,卷十四,小說門,小說,p 1180</note><note type="price">七分</note><identifier type="mh">book_8138</identifier></mods>