<mods xmlns="http://www.loc.gov/mods/v3" xmlns:xsi="http://www.w3.org/2001/XMLSchema-instance"
    xmlns:xlink="http://www.w3.org/1999/xlink" version="3.6"
    xsi:schemaLocation="http://www.loc.gov/mods/v3 http://cluster-schemas.uni-hd.de/modsCluster.xsd"
    ID="uuid-8D114861-EBB2-40DC-9DF5-1FB6AB38E30E">
    <name type="personal" xlink:href="">
        <namePart lang="chi" script="Hant">渡邊華山</namePart>
        <role>
            <roleTerm type="text">author</roleTerm>
        </role>
    </name>
    <titleInfo lang="chi" script="Hant">
        <title>鴂舌小記 《日本文庫》第二篇之內 </title>
    </titleInfo>
    <note type="citation">日本書目志,卷四,圖史門,日本史,p 714</note>
    <note type="price">二角五分</note>
    <identifier type="mh">book_2377</identifier>
</mods>
