<mods xmlns="http://www.loc.gov/mods/v3" xmlns:xsi="http://www.w3.org/2001/XMLSchema-instance"
    xmlns:xlink="http://www.w3.org/1999/xlink" version="3.6"
    xsi:schemaLocation="http://www.loc.gov/mods/v3 http://cluster-schemas.uni-hd.de/modsCluster.xsd"
    ID="uuid-3F4FCE95-16DA-490E-853E-4F5CC907E7A3">
    <name type="personal" xlink:href="">
        <namePart lang="chi" script="Hant">橫尾健太、鏑木由五郎著</namePart>
        <role>
            <roleTerm type="text">author</roleTerm>
        </role>
    </name>
    <titleInfo lang="chi" script="Hant">
        <title>米國養雞法</title>
    </titleInfo>
    <note type="citation">日本書目志,卷七,農業門,畜牧書,p 849</note>
    <note type="price">七角五分</note>
    <identifier type="mh">book_3860</identifier>
</mods>
